nlsql/ai_assistant/groq.py
nlsql/ai_assistant/local_llm.py
nlsql/api/server.py
nlsql/db/psql.py
nlsql/helpers.py
nlsql/main.py
nlsql/prompts/text_to_sql_prompt.py
nlsql-0.0.2.dist-info/LICENSE
nlsql-0.0.2.dist-info/METADATA
nlsql-0.0.2.dist-info/WHEEL
nlsql-0.0.2.dist-info/entry_points.txt
nlsql-0.0.2.dist-info/RECORD
