Metadata-Version: 2.1
Name: nlsql
Version: 0.0.2
Summary: generates SQL query from natural language for your PostrgreSQL database 
License: MIT
Keywords: postgres,sql,text-to-sq,llm
Author: Prashant Bhatkal
Author-email: prashantbhatkal2000@gmail.com
Requires-Python: >=3.8,<4.0
Classifier: License :: OSI Approved :: MIT License
Classifier: Programming Language :: Python :: 3
Classifier: Programming Language :: Python :: 3.8
Classifier: Programming Language :: Python :: 3.9
Classifier: Programming Language :: Python :: 3.10
Classifier: Programming Language :: Python :: 3.11
Classifier: Programming Language :: Python :: 3.12
Requires-Dist: Jinja2 (>=3.1.2)
Requires-Dist: fastapi (>=0.110.2)
Requires-Dist: groq (>=0.9.0)
Requires-Dist: llama-cpp-python (>=0.2.61)
Requires-Dist: psycopg2 (>=2.9.9)
Requires-Dist: pydantic (>=2.7.1)
Requires-Dist: uvicorn (>=0.29.0)
